{
  "version": 1,
  "mission_slug": "teamspace-event-contract-foundation-01KQHDE4",
  "mission_id": "01KQHDE43F53RJJ5824QB544XD",
  "mission_branch": "kitty/mission-teamspace-event-contract-foundation-01KQHDE4",
  "target_branch": "main",
  "lanes": [
    {
      "lane_id": "lane-a",
      "wp_ids": [
        "WP01",
        "WP02",
        "WP03",
        "WP04",
        "WP05",
        "WP06",
        "WP07"
      ],
      "write_scope": [
        "CHANGELOG.md",
        "COMPATIBILITY.md",
        "kitty-specs/teamspace-event-contract-foundation-01KQHDE4/contracts/.review-handoff.md",
        "kitty-specs/teamspace-event-contract-foundation-01KQHDE4/contracts/payload-reconciliation.md",
        "pyproject.toml",
        "src/spec_kitty_events/conformance/README.md",
        "src/spec_kitty_events/conformance/fixtures/**",
        "src/spec_kitty_events/forbidden_keys.py",
        "src/spec_kitty_events/lifecycle.py",
        "src/spec_kitty_events/schemas/generate.py",
        "src/spec_kitty_events/schemas/mission_closed_payload.schema.json",
        "src/spec_kitty_events/schemas/mission_created_payload.schema.json",
        "src/spec_kitty_events/schemas/status_transition_payload.schema.json",
        "src/spec_kitty_events/status.py",
        "src/spec_kitty_events/validation_errors.py",
        "tests/test_conformance_classes.py",
        "tests/test_fixture_determinism.py",
        "tests/test_forbidden_keys.py",
        "tests/test_lane_vocabulary.py",
        "tests/test_payload_reconciliation.py",
        "tests/test_validation_benchmark.py",
        "tests/test_validation_error.py"
      ],
      "predicted_surfaces": [
        "api",
        "app-shell",
        "artifact-rendering",
        "legacy-cleanup",
        "tests",
        "tracker-integration",
        "workspace"
      ],
      "depends_on_lanes": [],
      "parallel_group": 0
    }
  ],
  "computed_at": "2026-05-01T09:57:13.814604+00:00",
  "computed_from": "dependency_graph+ownership",
  "planning_artifact_wps": [],
  "collapse_report": {
    "events": [
      {
        "wp_a": "WP02",
        "wp_b": "WP01",
        "rule": "dependency",
        "evidence": "WP02 depends on WP01"
      },
      {
        "wp_a": "WP03",
        "wp_b": "WP02",
        "rule": "dependency",
        "evidence": "WP03 depends on WP02"
      },
      {
        "wp_a": "WP04",
        "wp_b": "WP01",
        "rule": "dependency",
        "evidence": "WP04 depends on WP01"
      },
      {
        "wp_a": "WP05",
        "wp_b": "WP01",
        "rule": "dependency",
        "evidence": "WP05 depends on WP01"
      },
      {
        "wp_a": "WP06",
        "wp_b": "WP01",
        "rule": "dependency",
        "evidence": "WP06 depends on WP01"
      },
      {
        "wp_a": "WP07",
        "wp_b": "WP01",
        "rule": "dependency",
        "evidence": "WP07 depends on WP01"
      }
    ],
    "total_merges": 6,
    "independent_wps_collapsed": 0,
    "by_rule": {
      "dependency": 6
    }
  }
}
